<?xml version="1.0" encoding="utf-8"?>
<ledger-demo>
  <demo-files>
    <file name="Val-9251.dat" path="..\test\nledger\sandbox\Val-9251.dat" />
    <file name="Val-9673.dat" path="..\test\nledger\sandbox\Val-9673.dat" />
    <file name="Val-2680.dat" path="..\test\nledger\sandbox\Val-2680.dat" />
    <file name="Val-3858.dat" path="..\test\nledger\sandbox\Val-3858.dat" />
    <file name="990E0D1.dat" path="..\test\nledger\sandbox\990E0D1.dat" />
    <file name="Val-2194.dat" path="..\test\nledger\sandbox\Val-2194.dat" />
    <file name="Val-3943.dat" path="..\test\nledger\sandbox\Val-3943.dat" />
    <file name="Val-3780.dat" path="..\test\nledger\sandbox\Val-3780.dat" />
    <file name="Val-2558.dat" path="..\test\nledger\sandbox\Val-2558.dat" />
    <file name="Val-9802.dat" path="..\test\nledger\sandbox\Val-9802.dat" />
    <file name="Val-2865.dat" path="..\test\nledger\sandbox\Val-2865.dat" />
    <file name="Val-3202.dat" path="..\test\nledger\sandbox\Val-3202.dat" />
    <file name="Val-2815.dat" path="..\test\nledger\sandbox\Val-2815.dat" />
    <file name="94A99E8.dat" path="..\test\nledger\sandbox\94A99E8.dat" />
    <file name="Val-9780.dat" path="..\test\nledger\sandbox\Val-9780.dat" />
    <file name="Val-2394.dat" path="..\test\nledger\sandbox\Val-2394.dat" />
    <file name="Val-2977.dat" path="..\test\nledger\sandbox\Val-2977.dat" />
    <file name="Val-2987.dat" path="..\test\nledger\sandbox\Val-2987.dat" />
    <file name="Val-9601.dat" path="..\test\nledger\sandbox\Val-9601.dat" />
    <file name="Val-1849.dat" path="..\test\nledger\sandbox\Val-1849.dat" />
    <file name="DF3FEBE.dat" path="..\test\nledger\sandbox\DF3FEBE.dat" />
    <file name="Val-3348.dat" path="..\test\nledger\sandbox\Val-3348.dat" />
    <file name="Val-1930.dat" path="..\test\nledger\sandbox\Val-1930.dat" />
    <file name="Val-1186.dat" path="..\test\nledger\sandbox\Val-1186.dat" />
    <file name="Val-1945.dat" path="..\test\nledger\sandbox\Val-1945.dat" />
    <file name="Val-7779.dat" path="..\test\nledger\sandbox\Val-7779.dat" />
    <file name="Val-1539.dat" path="..\test\nledger\sandbox\Val-1539.dat" />
    <file name="Val-7421.dat" path="..\test\nledger\sandbox\Val-7421.dat" />
    <file name="Val-1422.dat" path="..\test\nledger\sandbox\Val-1422.dat" />
    <file name="Val-1769.dat" path="..\test\nledger\sandbox\Val-1769.dat" />
    <file name="Val-7533.dat" path="..\test\nledger\sandbox\Val-7533.dat" />
    <file name="Val-8168.dat" path="..\test\nledger\sandbox\Val-8168.dat" />
    <file name="Val-2436.dat" path="..\test\nledger\sandbox\Val-2436.dat" />
    <file name="Val-1551.dat" path="..\test\nledger\sandbox\Val-1551.dat" />
    <file name="Val-3532.dat" path="..\test\nledger\sandbox\Val-3532.dat" />
    <file name="Val-3487.dat" path="..\test\nledger\sandbox\Val-3487.dat" />
    <file name="Val-9625.dat" path="..\test\nledger\sandbox\Val-9625.dat" />
    <file name="Val-3042.dat" path="..\test\nledger\sandbox\Val-3042.dat" />
    <file name="9B43E57.dat" path="..\test\nledger\sandbox\9B43E57.dat" />
    <file name="Val-1799.dat" path="..\test\nledger\sandbox\Val-1799.dat" />
    <file name="Val-3549.dat" path="..\test\nledger\sandbox\Val-3549.dat" />
    <file name="Val-1862.dat" path="..\test\nledger\sandbox\Val-1862.dat" />
    <file name="Val-2533.dat" path="..\test\nledger\sandbox\Val-2533.dat" />
    <file name="03ACB97.dat" path="..\test\nledger\sandbox\03ACB97.dat" />
    <file name="Val-3364.dat" path="..\test\nledger\sandbox\Val-3364.dat" />
    <file name="Val-2466.dat" path="..\test\nledger\sandbox\Val-2466.dat" />
    <file name="Val-3763.dat" path="..\test\nledger\sandbox\Val-3763.dat" />
    <file name="Val-2427.dat" path="..\test\nledger\sandbox\Val-2427.dat" />
    <file name="Val-9835.dat" path="..\test\nledger\sandbox\Val-9835.dat" />
    <file name="Val-1263.dat" path="..\test\nledger\sandbox\Val-1263.dat" />
    <file name="Val-310.dat" path="..\test\nledger\sandbox\Val-310.dat" />
    <file name="Val-3987.dat" path="..\test\nledger\sandbox\Val-3987.dat" />
    <file name="Val-10166.dat" path="..\test\nledger\sandbox\Val-10166.dat" />
    <file name="Val-919.dat" path="..\test\nledger\sandbox\Val-919.dat" />
    <file name="Val-3439.dat" path="..\test\nledger\sandbox\Val-3439.dat" />
    <file name="Val-3004.dat" path="..\test\nledger\sandbox\Val-3004.dat" />
    <file name="Val-3847.dat" path="..\test\nledger\sandbox\Val-3847.dat" />
    <file name="DB128F3.dat" path="..\test\nledger\sandbox\DB128F3.dat" />
    <file name="Val-1923.dat" path="..\test\nledger\sandbox\Val-1923.dat" />
    <file name="Val-8196.dat" path="..\test\nledger\sandbox\Val-8196.dat" />
    <file name="drewr3.dat" path="..\test\input\drewr3.dat" />
    <file name="Val-9812.dat" path="..\test\nledger\sandbox\Val-9812.dat" />
    <file name="Val-4819.dat" path="..\test\nledger\sandbox\Val-4819.dat" />
    <file name="Val-10389.dat" path="..\test\nledger\sandbox\Val-10389.dat" />
    <file name="Val-1073.dat" path="..\test\nledger\sandbox\Val-1073.dat" />
    <file name="Val-1835.dat" path="..\test\nledger\sandbox\Val-1835.dat" />
    <file name="Val-3135.dat" path="..\test\nledger\sandbox\Val-3135.dat" />
    <file name="48F4E47.dat" path="..\test\nledger\sandbox\48F4E47.dat" />
    <file name="C371854.dat" path="..\test\nledger\sandbox\C371854.dat" />
    <file name="Val-10272.dat" path="..\test\nledger\sandbox\Val-10272.dat" />
    <file name="Val-2591.dat" path="..\test\nledger\sandbox\Val-2591.dat" />
    <file name="Val-9259.dat" path="..\test\nledger\sandbox\Val-9259.dat" />
    <file name="Val-2270.dat" path="..\test\nledger\sandbox\Val-2270.dat" />
    <file name="Val-3885.dat" path="..\test\nledger\sandbox\Val-3885.dat" />
    <file name="Val-2284.dat" path="..\test\nledger\sandbox\Val-2284.dat" />
    <file name="Val-3187.dat" path="..\test\nledger\sandbox\Val-3187.dat" />
    <file name="Val-3708.dat" path="..\test\nledger\sandbox\Val-3708.dat" />
    <file name="Val-6954.dat" path="..\test\nledger\sandbox\Val-6954.dat" />
    <file name="Val-7862.dat" path="..\test\nledger\sandbox\Val-7862.dat" />
    <file name="Val-1593.dat" path="..\test\nledger\sandbox\Val-1593.dat" />
    <file name="Val-3496.dat" path="..\test\nledger\sandbox\Val-3496.dat" />
    <file name="Val-8184.dat" path="..\test\nledger\sandbox\Val-8184.dat" />
    <file name="Val-9791.dat" path="..\test\nledger\sandbox\Val-9791.dat" />
    <file name="Val-1789.dat" path="..\test\nledger\sandbox\Val-1789.dat" />
    <file name="expr.dat" path="..\test\nledger\sandbox\expr.dat" />
    <file name="Val-3979.dat" path="..\test\nledger\sandbox\Val-3979.dat" />
    <file name="Val-3302.dat" path="..\test\nledger\sandbox\Val-3302.dat" />
    <file name="Val-3894.dat" path="..\test\nledger\sandbox\Val-3894.dat" />
    <file name="Val-6608.dat" path="..\test\nledger\sandbox\Val-6608.dat" />
    <file name="Val-2841.dat" path="..\test\nledger\sandbox\Val-2841.dat" />
    <file name="Val-8190.dat" path="..\test\nledger\sandbox\Val-8190.dat" />
    <file name="Val-2044.dat" path="..\test\nledger\sandbox\Val-2044.dat" />
    <file name="Val-2373.dat" path="..\test\nledger\sandbox\Val-2373.dat" />
    <file name="Val-885.dat" path="..\test\nledger\sandbox\Val-885.dat" />
    <file name="sample.dat" path="..\test\input\sample.dat" />
    <file name="A9349E4.dat" path="..\test\nledger\sandbox\A9349E4.dat" />
    <file name="Val-1131.dat" path="..\test\nledger\sandbox\Val-1131.dat" />
    <file name="Val-3874.dat" path="..\test\nledger\sandbox\Val-3874.dat" />
    <file name="Val-1637.dat" path="..\test\nledger\sandbox\Val-1637.dat" />
    <file name="Val-2503.dat" path="..\test\nledger\sandbox\Val-2503.dat" />
    <file name="Val-874.dat" path="..\test\nledger\sandbox\Val-874.dat" />
    <file name="Val-9240.dat" path="..\test\nledger\sandbox\Val-9240.dat" />
    <file name="Val-2853.dat" path="..\test\nledger\sandbox\Val-2853.dat" />
    <file name="Val-2519.dat" path="..\test\nledger\sandbox\Val-2519.dat" />
    <file name="Val-7581.dat" path="..\test\nledger\sandbox\Val-7581.dat" />
    <file name="Val-2945.dat" path="..\test\nledger\sandbox\Val-2945.dat" />
    <file name="Val-2954.dat" path="..\test\nledger\sandbox\Val-2954.dat" />
    <file name="396F24E.dat" path="..\test\nledger\sandbox\396F24E.dat" />
    <file name="Val-3829.dat" path="..\test\nledger\sandbox\Val-3829.dat" />
    <file name="Val-735.dat" path="..\test\nledger\sandbox\Val-735.dat" />
    <file name="Val-3431.dat" path="..\test\nledger\sandbox\Val-3431.dat" />
    <file name="Val-2902.dat" path="..\test\nledger\sandbox\Val-2902.dat" />
    <file name="Val-2827.dat" path="..\test\nledger\sandbox\Val-2827.dat" />
    <file name="Val-2512.dat" path="..\test\nledger\sandbox\Val-2512.dat" />
    <file name="AD068BA.dat" path="..\test\nledger\sandbox\AD068BA.dat" />
    <file name="Val-7545.dat" path="..\test\nledger\sandbox\Val-7545.dat" />
    <file name="Val-7521.dat" path="..\test\nledger\sandbox\Val-7521.dat" />
    <file name="582C8C2.dat" path="..\test\nledger\sandbox\582C8C2.dat" />
    <file name="Val-4153.dat" path="..\test\nledger\sandbox\Val-4153.dat" />
    <file name="Val-1953.dat" path="..\test\nledger\sandbox\Val-1953.dat" />
    <file name="Val-3454.dat" path="..\test\nledger\sandbox\Val-3454.dat" />
    <file name="2F1CB75.dat" path="..\test\nledger\sandbox\2F1CB75.dat" />
    <file name="Val-3771.dat" path="..\test\nledger\sandbox\Val-3771.dat" />
    <file name="Val-3121.dat" path="..\test\nledger\sandbox\Val-3121.dat" />
    <file name="Val-1303.dat" path="..\test\nledger\sandbox\Val-1303.dat" />
    <file name="Val-2883.dat" path="..\test\nledger\sandbox\Val-2883.dat" />
    <file name="Val-3472.dat" path="..\test\nledger\sandbox\Val-3472.dat" />
    <file name="6B43DD4.dat" path="..\test\nledger\sandbox\6B43DD4.dat" />
    <file name="Val-2964.dat" path="..\test\nledger\sandbox\Val-2964.dat" />
    <file name="Val-2218.dat" path="..\test\nledger\sandbox\Val-2218.dat" />
    <file name="Val-2655.dat" path="..\test\nledger\sandbox\Val-2655.dat" />
    <file name="6453542.dat" path="..\test\nledger\sandbox\6453542.dat" />
    <file name="Val-2248.dat" path="..\test\nledger\sandbox\Val-2248.dat" />
    <file name="Val-1670.dat" path="..\test\nledger\sandbox\Val-1670.dat" />
    <file name="Val-3917.dat" path="..\test\nledger\sandbox\Val-3917.dat" />
    <file name="Val-3931.dat" path="..\test\nledger\sandbox\Val-3931.dat" />
    <file name="Val-3176.dat" path="..\test\nledger\sandbox\Val-3176.dat" />
    <file name="ledger.dat" path="..\test\nledger\sandbox\ledger.dat" />
    <file name="Val-3702.dat" path="..\test\nledger\sandbox\Val-3702.dat" />
    <file name="94C5675.dat" path="..\test\nledger\sandbox\94C5675.dat" />
    <file name="Val-3905.dat" path="..\test\nledger\sandbox\Val-3905.dat" />
    <file name="Val-1938.dat" path="..\test\nledger\sandbox\Val-1938.dat" />
    <file name="Val-1313.dat" path="..\test\nledger\sandbox\Val-1313.dat" />
    <file name="Val-1961.dat" path="..\test\nledger\sandbox\Val-1961.dat" />
    <file name="Val-4110.dat" path="..\test\nledger\sandbox\Val-4110.dat" />
    <file name="E30B2FC.dat" path="..\test\nledger\sandbox\E30B2FC.dat" />
    <file name="Val-2670.dat" path="..\test\nledger\sandbox\Val-2670.dat" />
    <file name="example.dat" path="..\test\nledger\sandbox\example.dat" />
    <file name="Val-3996.dat" path="..\test\nledger\sandbox\Val-3996.dat" />
    <file name="Val-7559.dat" path="..\test\nledger\sandbox\Val-7559.dat" />
    <file name="83E1FB3.dat" path="..\test\nledger\sandbox\83E1FB3.dat" />
    <file name="Val-7507.dat" path="..\test\nledger\sandbox\Val-7507.dat" />
    <file name="Val-2600.dat" path="..\test\nledger\sandbox\Val-2600.dat" />
    <file name="Val-932.dat" path="..\test\nledger\sandbox\Val-932.dat" />
    <file name="814A366.dat" path="..\test\nledger\sandbox\814A366.dat" />
    <file name="Val-3051.dat" path="..\test\nledger\sandbox\Val-3051.dat" />
    <file name="Val-3418.dat" path="..\test\nledger\sandbox\Val-3418.dat" />
    <file name="Val-7660.dat" path="..\test\nledger\sandbox\Val-7660.dat" />
    <file name="Val-3817.dat" path="..\test\nledger\sandbox\Val-3817.dat" />
    <file name="Val-946.dat" path="..\test\nledger\sandbox\Val-946.dat" />
    <file name="Val-1655.dat" path="..\test\nledger\sandbox\Val-1655.dat" />
    <file name="Val-2927.dat" path="..\test\nledger\sandbox\Val-2927.dat" />
  </demo-files>
  <demo-cases>
    <case test-id="Val-310" command="ledger bal --file Val-310.dat" filename="Val-310.dat" />
    <case test-id="48DDF26" command="ledger -f ledger.dat balance" filename="ledger.dat" />
    <case test-id="48DDF26" command="ledger -f ledger.dat balance" filename="ledger.dat" />
    <case test-id="8C7295F" command="ledger -f ledger.dat register checking" filename="ledger.dat" />
    <case test-id="BB32EF2" command="ledger -f ledger.dat register Bell" filename="ledger.dat" />
    <case test-id="1071890" command="ledger -f drewr3.dat balance" filename="drewr3.dat" />
    <case test-id="5BF4D8E" command="ledger -f drewr3.dat balance Assets Liabilities" filename="drewr3.dat" />
    <case test-id="66E3A2C" command="ledger -f drewr3.dat register" filename="drewr3.dat" />
    <case test-id="96B0EB3" command="ledger -f drewr3.dat register Groceries" filename="drewr3.dat" />
    <case test-id="AECD64E" command="ledger -f drewr3.dat balance Groceries" filename="drewr3.dat" />
    <case test-id="C6BC57E" command="ledger -f drewr3.dat register payee &quot;Organic&quot;" filename="drewr3.dat" />
    <case test-id="B86F6A6" command="ledger -f drewr3.dat cleared" filename="drewr3.dat" />
    <case test-id="Val-735" command="ledger bal --file Val-735.dat" filename="Val-735.dat" />
    <case test-id="6B43DD4" command="ledger balance ^assets ^liabilities --file 6B43DD4.dat" filename="6B43DD4.dat" />
    <case test-id="6B43DD4" command="ledger balance ^assets ^liabilities --file 6B43DD4.dat" filename="6B43DD4.dat" />
    <case test-id="6B43DD4" command="ledger balance ^assets ^liabilities --file 6B43DD4.dat" filename="6B43DD4.dat" />
    <case test-id="DB128F3" command="ledger balance ^income ^expenses --file DB128F3.dat" filename="DB128F3.dat" />
    <case test-id="DB524E4" command="ledger -M register -f drewr3.dat expenses:auto" filename="drewr3.dat" />
    <case test-id="Val-874" command="ledger bal --file Val-874.dat" filename="Val-874.dat" />
    <case test-id="Val-885" command="ledger bal --file Val-885.dat" filename="Val-885.dat" />
    <case test-id="Val-874" command="ledger bal --file Val-874.dat" filename="Val-874.dat" />
    <case test-id="Val-919" command="ledger bal --file Val-919.dat" filename="Val-919.dat" />
    <case test-id="Val-932" command="ledger bal --file Val-932.dat" filename="Val-932.dat" />
    <case test-id="Val-946" command="ledger bal --file Val-946.dat" filename="Val-946.dat" />
    <case test-id="990E0D1" command="ledger balance --no-total --file 990E0D1.dat" filename="990E0D1.dat" />
    <case test-id="990E0D1" command="ledger balance --no-total --file 990E0D1.dat" filename="990E0D1.dat" />
    <case test-id="990E0D1" command="ledger balance --no-total --file 990E0D1.dat" filename="990E0D1.dat" />
    <case test-id="Val-1073" command="ledger bal --file Val-1073.dat" filename="Val-1073.dat" />
    <case test-id="Val-1131" command="ledger bal --file Val-1131.dat" filename="Val-1131.dat" />
    <case test-id="DF3FEBE" command="ledger --no-total balance Billable Project --file DF3FEBE.dat" filename="DF3FEBE.dat" />
    <case test-id="DF3FEBE" command="ledger --no-total balance Billable Project --file DF3FEBE.dat" filename="DF3FEBE.dat" />
    <case test-id="Val-1186" command="ledger bal --file Val-1186.dat" filename="Val-1186.dat" />
    <case test-id="48F4E47" command="ledger balance EverQuest --file 48F4E47.dat" filename="48F4E47.dat" />
    <case test-id="48F4E47" command="ledger balance EverQuest --file 48F4E47.dat" filename="48F4E47.dat" />
    <case test-id="48F4E47" command="ledger balance EverQuest --file 48F4E47.dat" filename="48F4E47.dat" />
    <case test-id="Val-1263" command="ledger bal --file Val-1263.dat" filename="Val-1263.dat" />
    <case test-id="Val-1303" command="ledger bal --file Val-1303.dat" filename="Val-1303.dat" />
    <case test-id="Val-1313" command="ledger bal --file Val-1313.dat" filename="Val-1313.dat" />
    <case test-id="396F24E" command="ledger --no-total bal not ^Assets --file 396F24E.dat" filename="396F24E.dat" />
    <case test-id="396F24E" command="ledger --no-total bal not ^Assets --file 396F24E.dat" filename="396F24E.dat" />
    <case test-id="396F24E" command="ledger --no-total bal not ^Assets --file 396F24E.dat" filename="396F24E.dat" />
    <case test-id="2F1CB75" command="ledger --real --no-total bal --file 2F1CB75.dat" filename="2F1CB75.dat" />
    <case test-id="Val-1422" command="ledger bal --file Val-1422.dat" filename="Val-1422.dat" />
    <case test-id="AD068BA" command="ledger --payee=code -P reg ^Assets --file AD068BA.dat" filename="AD068BA.dat" />
    <case test-id="AD068BA" command="ledger --payee=code -P reg ^Assets --file AD068BA.dat" filename="AD068BA.dat" />
    <case test-id="E30B2FC" command="ledger --payee=code -P reg ^Expenses and code School --file E30B2FC.dat" filename="E30B2FC.dat" />
    <case test-id="Val-1539" command="ledger bal --file Val-1539.dat" filename="Val-1539.dat" />
    <case test-id="Val-1551" command="ledger bal --file Val-1551.dat" filename="Val-1551.dat" />
    <case test-id="Val-1593" command="ledger bal --file Val-1593.dat" filename="Val-1593.dat" />
    <case test-id="Val-1637" command="ledger bal --file Val-1637.dat" filename="Val-1637.dat" />
    <case test-id="Val-1655" command="ledger bal --file Val-1655.dat" filename="Val-1655.dat" />
    <case test-id="Val-1670" command="ledger bal --file Val-1670.dat" filename="Val-1670.dat" />
    <case test-id="82150D9" command="ledger -f example.dat bal" filename="example.dat" />
    <case test-id="82150D9" command="ledger -f example.dat bal" filename="example.dat" />
    <case test-id="Val-1769" command="ledger bal --file Val-1769.dat" filename="Val-1769.dat" />
    <case test-id="Val-1789" command="ledger bal --file Val-1789.dat" filename="Val-1789.dat" />
    <case test-id="Val-1799" command="ledger bal --file Val-1799.dat" filename="Val-1799.dat" />
    <case test-id="Val-1835" command="ledger bal --file Val-1835.dat" filename="Val-1835.dat" />
    <case test-id="Val-1849" command="ledger bal --file Val-1849.dat" filename="Val-1849.dat" />
    <case test-id="Val-1862" command="ledger bal --file Val-1862.dat" filename="Val-1862.dat" />
    <case test-id="Val-1923" command="ledger bal --file Val-1923.dat" filename="Val-1923.dat" />
    <case test-id="Val-1930" command="ledger bal --file Val-1930.dat" filename="Val-1930.dat" />
    <case test-id="Val-1938" command="ledger bal --file Val-1938.dat" filename="Val-1938.dat" />
    <case test-id="Val-1945" command="ledger bal --file Val-1945.dat" filename="Val-1945.dat" />
    <case test-id="Val-1953" command="ledger bal --file Val-1953.dat" filename="Val-1953.dat" />
    <case test-id="Val-1961" command="ledger bal --file Val-1961.dat" filename="Val-1961.dat" />
    <case test-id="814A366" command="ledger reg -V food --file 814A366.dat" filename="814A366.dat" />
    <case test-id="814A366" command="ledger reg -V food --file 814A366.dat" filename="814A366.dat" />
    <case test-id="Val-2044" command="ledger bal --file Val-2044.dat" filename="Val-2044.dat" />
    <case test-id="Val-2062" command="ledger accounts &gt;&gt; Accounts.dat --file sample.dat" filename="sample.dat" />
    <case test-id="Val-2194" command="ledger bal --file Val-2194.dat" filename="Val-2194.dat" />
    <case test-id="Val-2218" command="ledger bal --file Val-2218.dat" filename="Val-2218.dat" />
    <case test-id="Val-2248" command="ledger bal --file Val-2248.dat" filename="Val-2248.dat" />
    <case test-id="Val-2270" command="ledger bal --file Val-2270.dat" filename="Val-2270.dat" />
    <case test-id="Val-2284" command="ledger bal --file Val-2284.dat" filename="Val-2284.dat" />
    <case test-id="94A99E8" command="ledger bal --no-total ^Exp --file 94A99E8.dat" filename="94A99E8.dat" />
    <case test-id="94A99E8" command="ledger bal --no-total ^Exp --file 94A99E8.dat" filename="94A99E8.dat" />
    <case test-id="83E1FB3" command="ledger balance --no-total --recursive-aliases ^Exp --file 83E1FB3.dat" filename="83E1FB3.dat" />
    <case test-id="83E1FB3" command="ledger balance --no-total --recursive-aliases ^Exp --file 83E1FB3.dat" filename="83E1FB3.dat" />
    <case test-id="Val-2373" command="ledger bal --file Val-2373.dat" filename="Val-2373.dat" />
    <case test-id="Val-2394" command="ledger bal --file Val-2394.dat" filename="Val-2394.dat" />
    <case test-id="Val-2427" command="ledger bal --file Val-2427.dat" filename="Val-2427.dat" />
    <case test-id="Val-2436" command="ledger bal --file Val-2436.dat" filename="Val-2436.dat" />
    <case test-id="Val-2466" command="ledger bal --file Val-2466.dat" filename="Val-2466.dat" />
    <case test-id="Val-2503" command="ledger bal --file Val-2503.dat" filename="Val-2503.dat" />
    <case test-id="Val-2512" command="ledger bal --file Val-2512.dat" filename="Val-2512.dat" />
    <case test-id="Val-2519" command="ledger bal --file Val-2519.dat" filename="Val-2519.dat" />
    <case test-id="Val-2533" command="ledger bal --file Val-2533.dat" filename="Val-2533.dat" />
    <case test-id="Val-2558" command="ledger bal --file Val-2558.dat" filename="Val-2558.dat" />
    <case test-id="Val-2591" command="ledger bal --file Val-2591.dat" filename="Val-2591.dat" />
    <case test-id="Val-2600" command="ledger bal --file Val-2600.dat" filename="Val-2600.dat" />
    <case test-id="Val-2655" command="ledger bal --file Val-2655.dat" filename="Val-2655.dat" />
    <case test-id="Val-2670" command="ledger bal --file Val-2670.dat" filename="Val-2670.dat" />
    <case test-id="Val-2680" command="ledger bal --file Val-2680.dat" filename="Val-2680.dat" />
    <case test-id="Val-2815" command="ledger bal --file Val-2815.dat" filename="Val-2815.dat" />
    <case test-id="Val-2827" command="ledger bal --file Val-2827.dat" filename="Val-2827.dat" />
    <case test-id="Val-2841" command="ledger bal --file Val-2841.dat" filename="Val-2841.dat" />
    <case test-id="Val-2853" command="ledger bal --file Val-2853.dat" filename="Val-2853.dat" />
    <case test-id="Val-2865" command="ledger bal --file Val-2865.dat" filename="Val-2865.dat" />
    <case test-id="Val-2883" command="ledger bal --file Val-2883.dat" filename="Val-2883.dat" />
    <case test-id="Val-2902" command="ledger bal --file Val-2902.dat" filename="Val-2902.dat" />
    <case test-id="Val-2945" command="ledger bal --file Val-2945.dat" filename="Val-2945.dat" />
    <case test-id="Val-2927" command="ledger bal --file Val-2927.dat" filename="Val-2927.dat" />
    <case test-id="Val-2945" command="ledger bal --file Val-2945.dat" filename="Val-2945.dat" />
    <case test-id="Val-2954" command="ledger bal --file Val-2954.dat" filename="Val-2954.dat" />
    <case test-id="Val-2964" command="ledger bal --file Val-2964.dat" filename="Val-2964.dat" />
    <case test-id="Val-2977" command="ledger bal --file Val-2977.dat" filename="Val-2977.dat" />
    <case test-id="Val-2987" command="ledger bal --file Val-2987.dat" filename="Val-2987.dat" />
    <case test-id="Val-3004" command="ledger bal --file Val-3004.dat" filename="Val-3004.dat" />
    <case test-id="Val-3042" command="ledger bal --file Val-3042.dat" filename="Val-3042.dat" />
    <case test-id="Val-3051" command="ledger bal --file Val-3051.dat" filename="Val-3051.dat" />
    <case test-id="9B43E57" command="ledger reg --file 9B43E57.dat" filename="9B43E57.dat" />
    <case test-id="9B43E57" command="ledger reg --file 9B43E57.dat" filename="9B43E57.dat" />
    <case test-id="Val-3121" command="ledger bal --file Val-3121.dat" filename="Val-3121.dat" />
    <case test-id="Val-3135" command="ledger bal --file Val-3135.dat" filename="Val-3135.dat" />
    <case test-id="Val-3176" command="ledger bal --file Val-3176.dat" filename="Val-3176.dat" />
    <case test-id="Val-3187" command="ledger bal --file Val-3187.dat" filename="Val-3187.dat" />
    <case test-id="Val-3202" command="ledger bal --file Val-3202.dat" filename="Val-3202.dat" />
    <case test-id="Val-3302" command="ledger bal --file Val-3302.dat" filename="Val-3302.dat" />
    <case test-id="Val-3348" command="ledger bal --file Val-3348.dat" filename="Val-3348.dat" />
    <case test-id="Val-3364" command="ledger bal --file Val-3364.dat" filename="Val-3364.dat" />
    <case test-id="Val-3472" command="ledger bal --file Val-3472.dat" filename="Val-3472.dat" />
    <case test-id="Val-3439" command="ledger bal --file Val-3439.dat" filename="Val-3439.dat" />
    <case test-id="Val-3418" command="ledger bal --file Val-3418.dat" filename="Val-3418.dat" />
    <case test-id="Val-3431" command="ledger bal --file Val-3431.dat" filename="Val-3431.dat" />
    <case test-id="Val-3439" command="ledger bal --file Val-3439.dat" filename="Val-3439.dat" />
    <case test-id="Val-3454" command="ledger bal --file Val-3454.dat" filename="Val-3454.dat" />
    <case test-id="Val-3472" command="ledger bal --file Val-3472.dat" filename="Val-3472.dat" />
    <case test-id="Val-3487" command="ledger bal --file Val-3487.dat" filename="Val-3487.dat" />
    <case test-id="Val-3496" command="ledger bal --file Val-3496.dat" filename="Val-3496.dat" />
    <case test-id="Val-3532" command="ledger bal --file Val-3532.dat" filename="Val-3532.dat" />
    <case test-id="Val-3549" command="ledger bal --file Val-3549.dat" filename="Val-3549.dat" />
    <case test-id="Val-3702" command="ledger bal --file Val-3702.dat" filename="Val-3702.dat" />
    <case test-id="Val-3708" command="ledger bal --file Val-3708.dat" filename="Val-3708.dat" />
    <case test-id="Val-3763" command="ledger bal --file Val-3763.dat" filename="Val-3763.dat" />
    <case test-id="Val-3771" command="ledger bal --file Val-3771.dat" filename="Val-3771.dat" />
    <case test-id="Val-3780" command="ledger bal --file Val-3780.dat" filename="Val-3780.dat" />
    <case test-id="Val-3817" command="ledger bal --file Val-3817.dat" filename="Val-3817.dat" />
    <case test-id="Val-3829" command="ledger bal --file Val-3829.dat" filename="Val-3829.dat" />
    <case test-id="Val-3847" command="ledger bal --file Val-3847.dat" filename="Val-3847.dat" />
    <case test-id="Val-3858" command="ledger bal --file Val-3858.dat" filename="Val-3858.dat" />
    <case test-id="Val-3874" command="ledger bal --file Val-3874.dat" filename="Val-3874.dat" />
    <case test-id="Val-3885" command="ledger bal --file Val-3885.dat" filename="Val-3885.dat" />
    <case test-id="Val-3894" command="ledger bal --file Val-3894.dat" filename="Val-3894.dat" />
    <case test-id="Val-3905" command="ledger bal --file Val-3905.dat" filename="Val-3905.dat" />
    <case test-id="Val-3917" command="ledger bal --file Val-3917.dat" filename="Val-3917.dat" />
    <case test-id="Val-3931" command="ledger bal --file Val-3931.dat" filename="Val-3931.dat" />
    <case test-id="Val-3943" command="ledger bal --file Val-3943.dat" filename="Val-3943.dat" />
    <case test-id="Val-3979" command="ledger bal --file Val-3979.dat" filename="Val-3979.dat" />
    <case test-id="Val-3987" command="ledger bal --file Val-3987.dat" filename="Val-3987.dat" />
    <case test-id="Val-3996" command="ledger bal --file Val-3996.dat" filename="Val-3996.dat" />
    <case test-id="Val-4004" command="ledger --begin 2008/01/01 --end 2008/01/14 bal Income --file sample.dat" filename="sample.dat" />
    <case test-id="Val-4011" command="ledger --effective --begin 2008/01/01 --end 2008/01/14 bal Income --file sample.dat" filename="sample.dat" />
    <case test-id="6453542" command="ledger --effective register Groceries --file 6453542.dat" filename="6453542.dat" />
    <case test-id="6453542" command="ledger --effective register Groceries --file 6453542.dat" filename="6453542.dat" />
    <case test-id="C371854" command="ledger balance Liabilities:Huquq --file C371854.dat" filename="C371854.dat" />
    <case test-id="C371854" command="ledger balance Liabilities:Huquq --file C371854.dat" filename="C371854.dat" />
    <case test-id="Val-4110" command="ledger bal --file Val-4110.dat" filename="Val-4110.dat" />
    <case test-id="C371854" command="ledger balance Liabilities:Huquq --file C371854.dat" filename="C371854.dat" />
    <case test-id="Val-4153" command="ledger bal --file Val-4153.dat" filename="Val-4153.dat" />
    <case test-id="1D00D56" command="ledger balance -f drewr3.dat" filename="drewr3.dat" />
    <case test-id="06B2AD4" command="ledger balance -f drewr3.dat Auto MasterCard" filename="drewr3.dat" />
    <case test-id="B0468E1" command="ledger balance -f drewr3.dat Income" filename="drewr3.dat" />
    <case test-id="EAE389F" command="ledger balance -f drewr3.dat ^Bo" filename="drewr3.dat" />
    <case test-id="E2AF6AD" command="ledger balance -f drewr3.dat Bo" filename="drewr3.dat" />
    <case test-id="Val-4291" command="ledger balance Auto:Fuel and Chevron --file sample.dat" filename="sample.dat" />
    <case test-id="Val-4295" command="ledger balance --limit 'account=~/Fuel/' and 'payee=~/Chev/' --file sample.dat" filename="sample.dat" />
    <case test-id="Val-4309" command="ledger bal Expenses and not (Expenses:Drinks or Expenses:Candy or Expenses:Gifts) --file sample.dat" filename="sample.dat" />
    <case test-id="Val-4327" command="ledger -b &quot;last oct&quot; -S T bal ^expenses --file sample.dat" filename="sample.dat" />
    <case test-id="Val-4350" command="ledger -M --period-sort &quot;(amount)&quot; reg ^expenses --file sample.dat" filename="sample.dat" />
    <case test-id="Val-4358" command="ledger -M --period-sort &quot;(amount)&quot; -r reg ^expenses --file sample.dat" filename="sample.dat" />
    <case test-id="Val-4368" command="ledger -M -r --display 'account=~/mastercard/' reg ^expenses --file sample.dat" filename="sample.dat" />
    <case test-id="Val-4379" command="ledger -s -r --display &quot;account=~/mastercard/&quot; reg ^expenses --file sample.dat" filename="sample.dat" />
    <case test-id="582C8C2" command="ledger bal Allocation --current --format &quot;        %-17((depth_spacer)+(partial_account))        %10(percent(market(display_total), market(parent.total)))        %16(market(display_total))\n%/&quot; --file 582C8C2.dat" filename="582C8C2.dat" />
    <case test-id="582C8C2" command="ledger bal Allocation --current --format &quot;        %-17((depth_spacer)+(partial_account))        %10(percent(market(display_total), market(parent.total)))        %16(market(display_total))\n%/&quot; --file 582C8C2.dat" filename="582C8C2.dat" />
    <case test-id="Val-4819" command="ledger bal --file Val-4819.dat" filename="Val-4819.dat" />
    <case test-id="03ACB97" command="ledger xact 2004/4/9 viva food 11 tips 2.50 --file 03ACB97.dat" filename="03ACB97.dat" />
    <case test-id="03ACB97" command="ledger xact 2004/4/9 viva food 11 tips 2.50 --file 03ACB97.dat" filename="03ACB97.dat" />
    <case test-id="Val-5558" command="ledger bal rent food movies payee freddie --file sample.dat" filename="sample.dat" />
    <case test-id="Val-5565" command="ledger bal rent food movies @freddie --file sample.dat" filename="sample.dat" />
    <case test-id="A9349E4" command="ledger --options bal --cleared --file A9349E4.dat" filename="A9349E4.dat" />
    <case test-id="A76BB56" command="ledger -f drewr3.dat bal --no-total --master-account HUMBUG" filename="drewr3.dat" />
    <case test-id="Val-6290" command="ledger reg Expenses --begin Dec --bold-if &quot;amount&gt;100&quot; --file sample.dat" filename="sample.dat" />
    <case test-id="Val-6496" command="ledger reg Expenses --dow --collapse --file sample.dat" filename="sample.dat" />
    <case test-id="Val-6576" command="ledger reg Expenses --group-by &quot;payee&quot; --group-title-format &quot;------------------------ %-20(value) ---------------------\n&quot; --file sample.dat" filename="sample.dat" />
    <case test-id="Val-6608" command="ledger bal --file Val-6608.dat" filename="Val-6608.dat" />
    <case test-id="Val-6730" command="ledger bal Fuel --pivot &quot;Car&quot; --period &quot;this year&quot; --file sample.dat" filename="sample.dat" />
    <case test-id="Val-6954" command="ledger bal --file Val-6954.dat" filename="Val-6954.dat" />
    <case test-id="Val-7011" command="ledger -M --period-sort total reg ^Expenses --file sample.dat" filename="sample.dat" />
    <case test-id="94C5675" command="ledger -f 94C5675.dat -r register food" filename="94C5675.dat" />
    <case test-id="94C5675" command="ledger -f 94C5675.dat -r register food" filename="94C5675.dat" />
    <case test-id="Val-7257" command="ledger -d &quot;d&gt;=[last month]&quot; reg checking --file sample.dat" filename="sample.dat" />
    <case test-id="Val-7265" command="ledger -p &quot;last month&quot; reg checking --file sample.dat" filename="sample.dat" />
    <case test-id="Val-7421" command="ledger bal --file Val-7421.dat" filename="Val-7421.dat" />
    <case test-id="Val-7507" command="ledger bal --file Val-7507.dat" filename="Val-7507.dat" />
    <case test-id="Val-7521" command="ledger bal --file Val-7521.dat" filename="Val-7521.dat" />
    <case test-id="Val-7533" command="ledger bal --file Val-7533.dat" filename="Val-7533.dat" />
    <case test-id="Val-7545" command="ledger bal --file Val-7545.dat" filename="Val-7545.dat" />
    <case test-id="Val-7559" command="ledger bal --file Val-7559.dat" filename="Val-7559.dat" />
    <case test-id="Val-7581" command="ledger bal --file Val-7581.dat" filename="Val-7581.dat" />
    <case test-id="Val-7779" command="ledger bal --file Val-7779.dat" filename="Val-7779.dat" />
    <case test-id="Val-7800" command="ledger -p &quot;this year&quot; --monthly --average register ^expenses --file sample.dat" filename="sample.dat" />
    <case test-id="Val-7810" command="ledger --monthly register ^expenses --file sample.dat" filename="sample.dat" />
    <case test-id="Val-7816" command="ledger --budget --monthly register ^expenses --file sample.dat" filename="sample.dat" />
    <case test-id="Val-7825" command="ledger --unbudgeted --monthly register ^expenses --file sample.dat" filename="sample.dat" />
    <case test-id="Val-7851" command="ledger --forecast &quot;d&lt;[2010]&quot; bal ^assets ^liabilities --file sample.dat" filename="sample.dat" />
    <case test-id="Val-7862" command="ledger bal --file Val-7862.dat" filename="Val-7862.dat" />
    <case test-id="Val-7933" command="ledger -d &quot;d&gt;[this month]&quot; register checking --file sample.dat" filename="sample.dat" />
    <case test-id="Val-7942" command="ledger -b &quot;this month&quot; register checking --file sample.dat" filename="sample.dat" />
    <case test-id="Val-8184" command="ledger bal --file Val-8184.dat" filename="Val-8184.dat" />
    <case test-id="Val-8168" command="ledger bal --file Val-8168.dat" filename="Val-8168.dat" />
    <case test-id="Val-8184" command="ledger bal --file Val-8184.dat" filename="Val-8184.dat" />
    <case test-id="Val-8190" command="ledger bal --file Val-8190.dat" filename="Val-8190.dat" />
    <case test-id="Val-8196" command="ledger bal --file Val-8196.dat" filename="Val-8196.dat" />
    <case test-id="3406FC1" command="ledger -f expr.dat --format &quot;%(account) %(abs(amount))\n&quot; reg assets" filename="expr.dat" />
    <case test-id="3406FC1" command="ledger -f expr.dat --format &quot;%(account) %(abs(amount))\n&quot; reg assets" filename="expr.dat" />
    <case test-id="4D836EE" command="ledger -f expr.dat --format &quot;%(ansify_if(account, blue, options.color))\n&quot; reg" filename="expr.dat" />
    <case test-id="FF9C18C" command="ledger -f expr.dat --format &quot;%(account) %(ceiling(amount))\n&quot; reg" filename="expr.dat" />
    <case test-id="46FCFD3" command="ledger -f expr.dat --format &quot;%(account) %(code)\n&quot; reg assets" filename="expr.dat" />
    <case test-id="2CD27D7" command="ledger -f expr.dat --format &quot;%(account) %(commodity)\n&quot; reg" filename="expr.dat" />
    <case test-id="67EBA45" command="ledger -f expr.dat --format &quot;%(date) %(account)\n&quot; reg assets" filename="expr.dat" />
    <case test-id="4FDC7C5" command="ledger -f expr.dat --format &quot;%(account) %(floor(amount))\n&quot; reg" filename="expr.dat" />
    <case test-id="9605B13" command="ledger -f expr.dat --format &quot;%(format_date(date, '%A, %B %d. %Y'))\n&quot; reg assets" filename="expr.dat" />
    <case test-id="082FB27" command="ledger -f expr.dat --format &quot;»%(justify(account, 30, 30, true))«\n&quot; reg" filename="expr.dat" />
    <case test-id="C1FC7A7" command="ledger -f expr.dat -X $ -D --format &quot;%(options.daily) %(options.exchange)\n&quot; reg assets" filename="expr.dat" />
    <case test-id="04959BF" command="ledger -f expr.dat --format &quot;%(percent(amount, 200))\n&quot; reg" filename="expr.dat" />
    <case test-id="EAD8AA7" command="ledger -f expr.dat --format &quot;%(quoted(account)) %(quoted(amount))\n&quot; reg" filename="expr.dat" />
    <case test-id="0B0CBA1" command="ledger -f expr.dat --format &quot;%(1 + to_int('1'))\n%(2,5 + int(2,5))\n&quot; reg assets" filename="expr.dat" />
    <case test-id="F2FDF4B" command="ledger -f expr.dat --now 2015/01/01 --format &quot;%(today)\n&quot; reg assets" filename="expr.dat" />
    <case test-id="377BBAB" command="ledger -f expr.dat --format &quot;»%(trim(' 	Trimmed	 '))«\n&quot; reg assets" filename="expr.dat" />
    <case test-id="6F90EFC" command="ledger -f expr.dat --format &quot;%%\n&quot; reg assets" filename="expr.dat" />
    <case test-id="494256E" command="ledger -f expr.dat --format &quot;%12(5*O)\n&quot; reg assets" filename="expr.dat" />
    <case test-id="2B669C9" command="ledger -f expr.dat --format &quot;%B\n&quot; reg assets" filename="expr.dat" />
    <case test-id="F6E356F" command="ledger -f expr.dat --format &quot;%b\n&quot; reg assets" filename="expr.dat" />
    <case test-id="0E55246" command="ledger -f expr.dat --format &quot;%E\n&quot; reg assets" filename="expr.dat" />
    <case test-id="A26F4C0" command="ledger -f expr.dat --format &quot;%e\n&quot; reg assets" filename="expr.dat" />
    <case test-id="C1CAAF3" command="ledger -f expr.dat --format &quot;%C\n&quot; reg assets" filename="expr.dat" />
    <case test-id="F41A9BB" command="ledger -f expr.dat --format &quot;%P\n&quot; reg assets" filename="expr.dat" />
    <case test-id="29A70DD" command="ledger -f expr.dat --format &quot;%A\n&quot; reg" filename="expr.dat" />
    <case test-id="E6DC93A" command="ledger -f expr.dat --format &quot;%N\n&quot; reg assets" filename="expr.dat" />
    <case test-id="E80897D" command="ledger -f expr.dat --format &quot;%P\n%/%A\n&quot; reg" filename="expr.dat" />
    <case test-id="Val-9240" command="ledger bal --file Val-9240.dat" filename="Val-9240.dat" />
    <case test-id="Val-9251" command="ledger bal --file Val-9251.dat" filename="Val-9251.dat" />
    <case test-id="Val-9259" command="ledger bal --file Val-9259.dat" filename="Val-9259.dat" />
    <case test-id="Val-9601" command="ledger bal --file Val-9601.dat" filename="Val-9601.dat" />
    <case test-id="Val-9625" command="ledger bal --file Val-9625.dat" filename="Val-9625.dat" />
    <case test-id="Val-9673" command="ledger bal --file Val-9673.dat" filename="Val-9673.dat" />
    <case test-id="Val-9780" command="ledger bal --file Val-9780.dat" filename="Val-9780.dat" />
    <case test-id="Val-9791" command="ledger bal --file Val-9791.dat" filename="Val-9791.dat" />
    <case test-id="Val-9802" command="ledger bal --file Val-9802.dat" filename="Val-9802.dat" />
    <case test-id="Val-9812" command="ledger bal --file Val-9812.dat" filename="Val-9812.dat" />
    <case test-id="Val-9835" command="ledger bal --file Val-9835.dat" filename="Val-9835.dat" />
    <case test-id="Val-10031" command="ledger query &quot;/Book/&quot; --file sample.dat" filename="sample.dat" />
    <case test-id="Val-10166" command="ledger bal --file Val-10166.dat" filename="Val-10166.dat" />
    <case test-id="Val-10272" command="ledger bal --file Val-10272.dat" filename="Val-10272.dat" />
    <case test-id="Val-10367" command="ledger --group-by &quot;tag('trip')&quot; bal --file sample.dat" filename="sample.dat" />
    <case test-id="Val-10376" command="ledger cleared VWCU NFCU Tithe Misentry --file sample.dat" filename="sample.dat" />
    <case test-id="Val-10379" command="ledger register Joint --uncleared --file sample.dat" filename="sample.dat" />
    <case test-id="Val-10382" command="ledger register Checking --sort d -d &quot;d&gt;[2011/04/01]&quot; until 2011/05/25 --file sample.dat" filename="sample.dat" />
    <case test-id="Val-10389" command="ledger bal --file Val-10389.dat" filename="Val-10389.dat" />
  </demo-cases>
</ledger-demo>